LICENSE
MANIFEST.in
README.md
requirements.txt
setup.py
scopelets/__init__.py
scopelets/_version
scopelets/ansiblelib.py
scopelets/balancelib.py
scopelets/blockdevices.py
scopelets.egg-info/PKG-INFO
scopelets.egg-info/SOURCES.txt
scopelets.egg-info/dependency_links.txt
scopelets.egg-info/requires.txt
scopelets.egg-info/top_level.txt