Metadata-Version: 1.1
Name: scopelets
Version: 0.2.0
Summary: Small Python utilities that are used in a number of other Scopely open source packages.
Home-page: https://github.com/scopely-devops/scopelets
Author: Mitch Garnaat
Author-email: mitch@scopely.com
License: Apache License
